sparkminiohandler/__init__.py
sparkminiohandler/spark_minio_handler.py
sparkminiohandler/sparkminiohandler.py
SparkMinIOHandle-0.0.7.dist-info/METADATA
SparkMinIOHandle-0.0.7.dist-info/WHEEL
SparkMinIOHandle-0.0.7.dist-info/top_level.txt
SparkMinIOHandle-0.0.7.dist-info/RECORD
