Metadata-Version: 2.1
Name: SparkMinIOHandle
Version: 0.0.7
Summary: Spark MinIO Handler Package
Home-page: UNKNOWN
Author: Yuri Dimitri
Author-email: yuridrcosta@gmail.com
License: UNKNOWN
Keywords: python,minio,pyspark
Platform: UNKNOWN
Classifier: Development Status :: 3 - Alpha
Classifier: Intended Audience :: Education
Classifier: Programming Language :: Python :: 2
Classifier: Programming Language :: Python :: 3
Classifier: Operating System :: MacOS :: MacOS X
Classifier: Operating System :: Microsoft :: Windows
Requires-Dist: minio
Requires-Dist: pyspark
Requires-Dist: pandas
